instatool/__init__.py
instatool-0.0.2.dist-info/LICENSES.txt
instatool-0.0.2.dist-info/METADATA
instatool-0.0.2.dist-info/WHEEL
instatool-0.0.2.dist-info/top_level.txt
instatool-0.0.2.dist-info/RECORD
